cgbenigma/__init__.py
cgbenigma/cgblib.py
cgbenigma-0.0.6.dist-info/METADATA
cgbenigma-0.0.6.dist-info/WHEEL
cgbenigma-0.0.6.dist-info/licenses/LICENSE
cgbenigma-0.0.6.dist-info/RECORD
