Metadata-Version: 2.4
Name: cgbenigma
Version: 0.0.6
Summary: Cipher library for encryption methods found on Chinese Gold Bars
Project-URL: Homepage, https://github.com/milton6310/cgbenigma
Project-URL: Issues, https://github.com/milton6310/cgbenigma/issues
Author-email: Milton Kim <milton6310@icloud.com>
License-Expression: MIT
License-File: LICENSE
Classifier: Operating System :: OS Independent
Classifier: Programming Language :: Python :: 3
Requires-Python: >=3.9
